LICENSES.txt
MANIFEST.in
README.md
REQUIREMENTS.txt
REQUIREMENTS_TEST.txt
setup.cfg
setup.py
pbcommand/__init__.py
pbcommand/common_options.py
pbcommand/interactive_resolver.py
pbcommand/resolver.py
pbcommand/utils.py
pbcommand/validators.py
pbcommand.egg-info/PKG-INFO
pbcommand.egg-info/SOURCES.txt
pbcommand.egg-info/dependency_links.txt
pbcommand.egg-info/entry_points.txt
pbcommand.egg-info/not-zip-safe
pbcommand.egg-info/requires.txt
pbcommand.egg-info/top_level.txt
pbcommand/cli/__init__.py
pbcommand/cli/core.py
pbcommand/cli/quick.py
pbcommand/cli/utils.py
pbcommand/cli/examples/__init__.py
pbcommand/cli/examples/dev_app.py
pbcommand/cli/examples/dev_gather_fasta_app.py
pbcommand/cli/examples/dev_mixed_app.py
pbcommand/cli/examples/dev_quick_hello_world.py
pbcommand/cli/examples/dev_scatter_fasta_app.py
pbcommand/cli/examples/dev_simple_app.py
pbcommand/cli/examples/dev_txt_app.py
pbcommand/cli/examples/template_simple.py
pbcommand/engine/__init__.py
pbcommand/engine/runner.py
pbcommand/models/__init__.py
pbcommand/models/common.py
pbcommand/models/conditions.py
pbcommand/models/parser.py
pbcommand/models/report.py
pbcommand/models/tool_contract.py
pbcommand/pb_io/__init__.py
pbcommand/pb_io/common.py
pbcommand/pb_io/conditions.py
pbcommand/pb_io/report.py
pbcommand/pb_io/tool_contract_io.py
pbcommand/schemas/__init__.py
pbcommand/schemas/pbreport.avsc
pbcommand/schemas/resolved_tool_contract.avsc
pbcommand/schemas/tool_contract.avsc
pbcommand/services/__init__.py
pbcommand/services/cli.py
pbcommand/services/models.py
pbcommand/services/service_access_layer.py
pbcommand/services/utils.py
pbcommand/testkit/__init__.py
pbcommand/testkit/base_utils.py
pbcommand/testkit/core.py
tests/__init__.py
tests/base_utils.py
tests/test_common_cmdline_core.py
tests/test_e2e_example_apps.py
tests/test_engine_runner.py
tests/test_load_resolved_tool_contract.py
tests/test_models_common.py
tests/test_models_report.py
tests/test_models_report_attribute.py
tests/test_models_report_column.py
tests/test_models_report_plot.py
tests/test_models_report_plotgroup.py
tests/test_models_report_table.py
tests/test_parsers.py
tests/test_pb_io_common.py
tests/test_pb_io_conditions.py
tests/test_pb_io_report.py
