Metadata-Version: 1.1
Name: pbcommand
Version: 0.3.29
Summary: Library and Tools for interfacing to PacBio pbsmrtpipe workflow engine.
Home-page: https://github.com/PacificBiosciences/pbcommand
Author: mpkocher natechols
Author-email: mkocher@pacificbiosciences.com
License: BSD
Download-URL: https://github.com/PacificBiosciences/pbcommand/tarball/0.3.29
Keywords: workflow,pacbio
Platform: UNKNOWN
Classifier: Development Status :: 4 - Beta
Classifier: Environment :: Console
Classifier: Topic :: Software Development :: Bug Tracking
